{
  "type": "file",
  "statements": [
    {
      "type": "namespaceStatement",
      "name": "a",
      "statements": [
        {
          "type": "functionStatement",
          "name": "function",
          "statements": [
            {
              "type": "callStatement",
              "func": {
                "type": "funcIdent",
                "path": [
                  "heyo"
                ]
              },
              "params": {
                "type": "callParams",
                "posits": [
                  {
                    "type": "bool",
                    "content": false
                  }
                ],
                "named": {}
              },
              "parens": false
            }
          ],
          "mctag": null
        }
      ]
    }
  ]
}
